voussoir/__init__.py
voussoir/cli.py
voussoir/pagewarper.py
pyvoussoir-0.3.1.dist-info/LICENSE
pyvoussoir-0.3.1.dist-info/METADATA
pyvoussoir-0.3.1.dist-info/WHEEL
pyvoussoir-0.3.1.dist-info/entry_points.txt
pyvoussoir-0.3.1.dist-info/top_level.txt
pyvoussoir-0.3.1.dist-info/RECORD
