Metadata-Version: 2.1
Name: pyvoussoir
Version: 0.3.1
Summary: Automatic de-keystoning/page-splitting tool for single camera book scanners
Home-page: https://github.com/hnesk/pyvoussoir
Author: Johannes Künsebeck
Author-email: kuensebeck@googlemail.com
License: ISC License
Keywords: OCR,page splitting,page dewarping,keystoning,perspective correction,voussoir
Platform: UNKNOWN
Classifier: Programming Language :: Python :: 3
Classifier: License :: OSI Approved :: ISC License (ISCL)
Classifier: Operating System :: OS Independent
Classifier: Development Status :: 4 - Beta
Classifier: Environment :: Console
Classifier: Topic :: Scientific/Engineering :: Image Recognition
Requires-Dist: docopt
Requires-Dist: numpy
Requires-Dist: opencv-python-headless
Requires-Dist: Pillow
Requires-Dist: schema
